multi/instr_mem.v
// instr_mem.v
// Instruction Memory (read-only) for Multi-Cycle Processor
// Initialized with test instructions as needed.

module instr_mem(
    input  [31:0] address, 
    output [31:0] instr
);
    reg [31:0] memory [255:0];
    initial begin
        // Initialize instruction memory (e.g., from a test program)
        // Example: memory[0] = 32'hXXXXXXXX;
        //memory[0] = 32'h20010005; // addi $1, $0, 5      => $1 = 5
    //    memory[1] = 32'h20020005; // addi $2, $0, 5      => $2 = 5
      //  memory[2] = 32'h10220001; // beq $1, $2, 1       => if equal, branch to PC+8
        //memory[3] = 32'h08000006; // j to address 0x18   => should be skipped
     //   memory[4] = 32'h20030001; // addi $3, $0, 1      => $3 = 1 (if branch taken)
       // memory[5] = 32'h08000006; // j 0x00000018        => HALT loop
    memory[0] = 32'h20010003; // addi $1, $0, 3
    memory[1] = 32'h20020004; // addi $2, $0, 4
    memory[2] = 32'h00221820; // add  $3, $1, $2
    memory[3] = 32'h00000000; // nop
    memory[4] = 32'hfc000000; // HALT (custom pattern)
    end
    // Word-aligned read
    assign instr = memory[address[31:2]];
endmodule

// data_mem.v
// Data Memory for Multi-Cycle Processor
// Supports synchronous write and asynchronous read (word-aligned).

module data_mem(
    input         clk,
    input         MemWrite,
    input  [31:0] address,
    input  [31:0] write_data,
    output [31:0] read_data
);
    reg [31:0] memory [255:0];
    // Write on rising clock edge if enabled
    always @(posedge clk) begin
        if (MemWrite) begin
            memory[address[31:2]] <= write_data;
        end
    end
    // Always output the data at the given address
    assign read_data = memory[address[31:2]];
endmodule

multi/register_file.v
// register_file.v
// 32x32 Register File (MIPS) for Multi-Cycle Processor
// Register 0 is hardwired to 0.

module regfile(
    input         clk,
    input         RegWrite,
    input  [4:0]  ra1,    // read address 1 (rs)
    input  [4:0]  ra2,    // read address 2 (rt)
    input  [4:0]  wa,     // write address (rd or rt)
    input  [31:0] wd,     // write data
    output [31:0] rd1,    // read data 1
    output [31:0] rd2     // read data 2
);
    reg [31:0] regs [31:0];
    integer i;
    initial begin
        // Initialize registers to zero (R0 remains 0 always)
        for (i = 0; i < 32; i = i + 1) begin
            regs[i] = 32'd0;
        end
    end

    // Combinational read ports
    assign rd1 = regs[ra1];
    assign rd2 = regs[ra2];

    // Synchronous write port
    always @(posedge clk) begin
        if (RegWrite && (wa != 0)) begin
            regs[wa] <= wd;
        end
    end
endmodule

multi/alu.v
// alu.v
// ALU module for Multi-Cycle MIPS Processor
// Supports add, sub, and, or, slt operations.

module ALU(
    input  [31:0] A,
    input  [31:0] B,
    input  [2:0]  ALUControl,
    output reg [31:0] Result,
    output Zero
);
    always @(*) begin
        case (ALUControl)
            3'b000: Result = A + B;                 // add
            3'b001: Result = A - B;                 // sub
            3'b010: Result = A & B;                 // and
            3'b011: Result = A | B;                 // or
            3'b100: Result = (A < B) ? 32'd1 : 32'd0; // slt (signed compare)
            default: Result = 32'd0;
        endcase
    end
    assign Zero = (Result == 32'd0);
endmodule

multi/datapath.v
// datapath.v
// Datapath module for Multi-Cycle MIPS Processor
//
// Contains PC, IR, MDR, register file A/B, ALU, and ALUOut register.
// Controlled by control signals to perform fetch, decode, execute, memory, and write-back steps.

module datapath(
    input         clk,             // clock
    input         reset,           // reset to initialize PC and registers
    input         PCWrite,         // enable PC write
    input         PCWriteCond,     // enable PC write on condition (branch)
    input         IorD,            // 0: use PC for memory addr (fetch), 1: use ALUOut (data access)
    input         MemRead,         // memory read
    input         MemWrite,        // memory write
    input         IRWrite,         // write to instruction register
    input         RegWrite,        // write to register file
    input         RegDst,          // 1: write to rd field, 0: write to rt field
    input         MemtoReg,        // 1: write memory data to reg, 0: write ALUOut to reg
    input         ALUSrcA,         // 0: ALU A = PC, 1: ALU A = A register
    input  [1:0]  ALUSrcB,         // 00: B reg, 01: constant 4, 10: sign-imm, 11: sign-imm<<2
    input  [1:0]  PCSource,        // 00: ALU result (PC+4), 01: ALUOut (branch target), 10: jump address
    input  [2:0]  ALUControl,      // ALU operation code (000=add,001=sub,010=and,011=or,100=slt)
    // Instruction memory interface
    output [31:0] PC,             // current program counter
    output [31:0] IR_out,         // current instruction (for control unit)
    input  [31:0] Instr,          // instruction fetched from instruction memory
    // Data memory interface
    output [31:0] ALUAddr,        // address for data memory (from ALUOut or PC)
    input  [31:0] MemDataIn,      // data read from data memory
    output [31:0] MemDataOut,     // data to write to data memory (from register B)
    output        MemReadOut,     // (unused externally)
    output        MemWriteOut,    // (unused externally)
    output        Zero            // ALU zero flag (for branch)
);

    // Internal registers
    reg [31:0] PC_reg;            // Program Counter register
    reg [31:0] IR;                // Instruction Register
    reg [31:0] MDR;               // Memory Data Register
    reg [31:0] A_reg;             // A register (first ALU operand from regfile)
    reg [31:0] B_reg;             // B register (second ALU operand from regfile)
    reg [31:0] ALUOut;            // ALU Output Register

    // MUX to select destination register (rd or rt)
    wire [4:0] WriteReg = RegDst ? IR[15:11] : IR[20:16];
    // MUX to select data to write to register file (from ALUOut or from memory via MDR)
    wire [31:0] WriteData = MemtoReg ? MDR : ALUOut;

    // Output assignments
    assign PC = PC_reg;
    assign IR_out = IR;
    assign ALUAddr = IorD ? ALUOut : PC_reg;  // Mem address = PC or ALUOut
    assign MemDataOut = B_reg;
    assign MemReadOut = MemRead;
    assign MemWriteOut = MemWrite;

    // Sign-extend immediate
    wire [31:0] SignImm = {{16{IR[15]}}, IR[15:0]};

    // ALU source multiplexers
    wire [31:0] ALU_src_A = ALUSrcA ? A_reg : PC_reg;
    reg  [31:0] ALU_src_B;
    always @(*) begin
        case (ALUSrcB)
            2'b00: ALU_src_B = B_reg;
            2'b01: ALU_src_B = 32'd4;
            2'b10: ALU_src_B = SignImm;
            2'b11: ALU_src_B = SignImm << 2;
            default: ALU_src_B = 32'd0;
        endcase
    end

    // Instantiate ALU
    wire [31:0] ALU_result;
    wire ALU_zero;
    ALU alu_inst (
        .A(ALU_src_A),
        .B(ALU_src_B),
        .ALUControl(ALUControl),
        .Result(ALU_result),
        .Zero(ALU_zero)
    );
    assign Zero = ALU_zero;

    // Instantiate register file
    wire [31:0] rd1, rd2;
    regfile regfile_inst (
        .clk(clk),
        .RegWrite(RegWrite),
        .ra1(IR[25:21]),  // rs
        .ra2(IR[20:16]),  // rt
        .wa(WriteReg),
        .wd(WriteData),
        .rd1(rd1),
        .rd2(rd2)
    );

    // Sequential logic
    // Update PC: either PC+4, branch target, or jump
    always @(posedge clk or posedge reset) begin
        if (reset) begin
            PC_reg <= 32'b0;
        end else if (PCWrite || (PCWriteCond && ALU_zero)) begin
            case (PCSource)
                2'b00: PC_reg <= ALU_result;  // PC + 4 (ALU result)
                2'b01: PC_reg <= ALUOut;      // branch target (ALUOut computed earlier)
                2'b10: PC_reg <= {PC_reg[31:28], IR[25:0], 2'b00}; // jump
                default: PC_reg <= ALU_result;
            endcase
        end
    end

    // Update IR on fetch
    always @(posedge clk) begin
        if (IRWrite) begin
            IR <= Instr;
        end
    end

    // Update MDR on memory read
    always @(posedge clk) begin
        if (MemRead) begin
            MDR <= MemDataIn;
        end
    end

    // Latch register file outputs into A and B each cycle
    always @(posedge clk) begin
        A_reg <= rd1;
        B_reg <= rd2;
    end

    // Capture ALU result
    always @(posedge clk) begin
        ALUOut <= ALU_result;
    end

endmodule

multi/control.v
// control.v
// Microprogrammed Control Unit for Multi-Cycle MIPS Processor
// Generates control signals for each microcycle state.

module control(
    input         clk,
    input         reset,
    input  [31:0] IR,          // instruction register
    input         Zero,        // ALU zero flag (for branch)
    output reg    PCWrite,
    output reg    PCWriteCond,
    output reg    IorD,
    output reg    MemRead,
    output reg    MemWrite,
    output reg    IRWrite,
    output reg    RegDst,
    output reg    MemtoReg,
    output reg    RegWrite,
    output reg    ALUSrcA,
    output reg [1:0] ALUSrcB,
    output reg [1:0] PCSource,
    output reg [2:0] ALUControl
);
    // State encoding
    parameter FETCH     = 4'd0;
    parameter DECODE    = 4'd1;
    parameter R_EXEC    = 4'd2;
    parameter R_WRITE   = 4'd3;
    parameter I_EXEC    = 4'd4;
    parameter MEM_ACCESS= 4'd5;
    parameter I_WRITE   = 4'd6;
    parameter BRANCH    = 4'd7;
    parameter JUMP      = 4'd8;

    reg [3:0] state, next_state;

    // Sequential state register
    always @(posedge clk or posedge reset) begin
        if (reset)
            state <= FETCH;
        else
            state <= next_state;
    end

    // Next-state logic and control outputs
    always @(*) begin
        // Default: all control signals low
        PCWrite      = 1'b0;
        PCWriteCond  = 1'b0;
        IorD         = 1'b0;
        MemRead      = 1'b0;
        MemWrite     = 1'b0;
        IRWrite      = 1'b0;
        RegDst       = 1'b0;
        MemtoReg     = 1'b0;
        RegWrite     = 1'b0;
        ALUSrcA      = 1'b0;
        ALUSrcB      = 2'b00;
        PCSource     = 2'b00;
        ALUControl   = 3'b000;
        next_state   = FETCH;

        case (state)
            FETCH: begin
                // Fetch instruction: M[PC] -> IR, PC <- PC+4
                MemRead   = 1'b1;
                IRWrite   = 1'b1;
                ALUSrcA   = 1'b0;
                ALUSrcB   = 2'b01;    // add 4
                ALUControl= 3'b000;   // add
                PCWrite   = 1'b1;
                next_state= DECODE;
            end

            DECODE: begin
                // Decode: compute branch target (ALUOut = PC + imm<<2)
                ALUSrcA   = 1'b0;
                ALUSrcB   = 2'b11;    // sign-imm << 2
                ALUControl= 3'b000;   // add
                // Dispatch based on opcode
                case (IR[31:26])
                    6'b000000: next_state = R_EXEC;    // R-type
                    6'b100011: next_state = I_EXEC;    // lw
                    6'b101011: next_state = I_EXEC;    // sw
                    6'b000100: next_state = BRANCH;    // beq
                    6'b001000: next_state = I_EXEC;    // addi
                    6'b000010: next_state = JUMP;      // j
                    default:   next_state = FETCH;
                endcase
            end

            R_EXEC: begin
                // R-type ALU execution: A op B
                ALUSrcA   = 1'b1;      // use register A = rs
                ALUSrcB   = 2'b00;     // use register B = rt
                // Determine ALU operation from funct field
                case (IR[5:0])
                    6'b100000: ALUControl = 3'b000; // add
                    6'b100010: ALUControl = 3'b001; // sub
                    6'b100100: ALUControl = 3'b010; // and
                    6'b100101: ALUControl = 3'b011; // or
                    6'b101010: ALUControl = 3'b100; // slt
                    default:   ALUControl = 3'b000;
                endcase
                next_state = R_WRITE;
            end

            R_WRITE: begin
                // Write result of R-type to regfile
                RegWrite  = 1'b1;
                RegDst    = 1'b1;      // write to rd
                MemtoReg  = 1'b0;      // from ALUOut
                next_state= FETCH;
            end

            I_EXEC: begin
                // I-type execution (lw/sw: compute address, addi: compute sum)
                ALUSrcA   = 1'b1;      // use register A = rs
                ALUSrcB   = 2'b10;     // sign-extended immediate
                ALUControl= 3'b000;    // add
                case (IR[31:26])
                    6'b100011: next_state = MEM_ACCESS; // lw
                    6'b101011: next_state = MEM_ACCESS; // sw
                    default:   next_state = I_WRITE;    // addi
                endcase
            end

            MEM_ACCESS: begin
                // Memory access for lw/sw
                IorD      = 1'b1;      // use ALUOut as address
                case (IR[31:26])
                    6'b100011: begin      // lw
                        MemRead = 1'b1;
                        next_state = I_WRITE;
                    end
                    6'b101011: begin      // sw
                        MemWrite= 1'b1;
                        next_state = FETCH;
                    end
                    default: begin
                        next_state = FETCH;
                    end
                endcase
            end

            I_WRITE: begin
                // Write-back for lw or addi
                RegWrite  = 1'b1;
                RegDst    = 1'b0;     // write to rt
                if (IR[31:26] == 6'b100011) begin
                    // lw
                    MemtoReg = 1'b1;  // write MDR
                end else begin
                    // addi
                    MemtoReg = 1'b0;  // write ALUOut
                end
                next_state = FETCH;
            end

            BRANCH: begin
                // Branch equal: if Zero, PC <- branch target
                PCWriteCond = 1'b1;
                PCSource    = 2'b01; // select ALUOut (branch target)
                next_state  = FETCH;
            end

            JUMP: begin
                // Jump: PC <- {PC+4[31:28], instr_index, 2'b00}
                PCWrite  = 1'b1;
                PCSource = 2'b10;
                next_state = FETCH;
            end

            default: begin
                next_state = FETCH;
            end
        endcase
    end

endmodule

multi/mips_multicycle.v
// mips_multicycle.v
// Top-level module for the Multi-Cycle MIPS Processor (Verilog).
// Instantiates the datapath, control unit, and memory modules.

module mips_multicycle(
    input        clk,
    input        reset
);
    // Wires for interconnecting modules
    wire [31:0] PC, Instr, ALUAddr, MemDataOut, MemDataIn, IR;
    wire Zero;
    // Control signals
    wire PCWrite, PCWriteCond, IorD, MemRead, MemWrite, IRWrite, RegDst, MemtoReg, RegWrite, ALUSrcA;
    wire [1:0] ALUSrcB, PCSource;
    wire [2:0] ALUControl;

    // Instantiate the Control Unit
    control ctrl_unit(
        .clk(clk),
        .reset(reset),
        .IR(IR),
        .Zero(Zero),
        .PCWrite(PCWrite),
        .PCWriteCond(PCWriteCond),
        .IorD(IorD),
        .MemRead(MemRead),
        .MemWrite(MemWrite),
        .IRWrite(IRWrite),
        .RegDst(RegDst),
        .MemtoReg(MemtoReg),
        .RegWrite(RegWrite),
        .ALUSrcA(ALUSrcA),
        .ALUSrcB(ALUSrcB),
        .PCSource(PCSource),
        .ALUControl(ALUControl)
    );

    // Instruction Memory (read-only)
    instr_mem instr_memory(
        .address(PC),
        .instr(Instr)
    );

    // Datapath
    datapath dp(
        .clk(clk),
        .reset(reset),
        .PCWrite(PCWrite),
        .PCWriteCond(PCWriteCond),
        .IorD(IorD),
        .MemRead(MemRead),
        .MemWrite(MemWrite),
        .IRWrite(IRWrite),
        .RegWrite(RegWrite),
        .RegDst(RegDst),
        .MemtoReg(MemtoReg),
        .ALUSrcA(ALUSrcA),
        .ALUSrcB(ALUSrcB),
        .PCSource(PCSource),
        .ALUControl(ALUControl),
        .PC(PC),
        .IR_out(IR),
        .Instr(Instr),
        .ALUAddr(ALUAddr),
        .MemDataIn(MemDataIn),
        .MemDataOut(MemDataOut),
        .MemReadOut(),       // not used externally
        .MemWriteOut(),      // not used externally
        .Zero(Zero)
    );

    // Data Memory
    data_mem data_memory(
        .clk(clk),
        .MemWrite(MemWrite),
        .address(ALUAddr),
        .write_data(MemDataOut),
        .read_data(MemDataIn)
    );

endmodule

multi/testbench.v
`timescale 1ns/1ps

module testbench;
    reg clk, reset;

    // Instantiate the processor
    mips_multicycle dut (
        .clk(clk),
        .reset(reset)
    );

    // Clock generation: 10ns period
    always #5 clk = ~clk;

    // VCD waveform output for GTKWave
    initial begin
        $dumpfile("simulation.vcd");
        $dumpvars(0, testbench);
    end

    initial begin
        // Initialize
        clk = 0;
        reset = 1;
        #10;
        reset = 0;

        $display("Time\tPC\tInstr\t\t$1\t$2\t$3");

        // Simulate up to 200 cycles unless HALT is hit
        repeat (200) begin
            @(posedge clk);
            #1;

            $display("%0t\t%h\t%h\t%0d\t%0d\t%0d",
                $time,
                dut.PC,
                dut.Instr,
                dut.dp.regfile_inst.regs[1],
                dut.dp.regfile_inst.regs[2],
                dut.dp.regfile_inst.regs[3]
            );

            // HALT detection: custom instruction fc000000
            if (dut.Instr == 32'hfc000000) begin
                $display("\nHALT instruction encountered at PC = %h", dut.PC);
                if (dut.dp.regfile_inst.regs[3] == 7)
                    $display("✅ PASS: $3 = 7 as expected");
                else
                    $display("❌ FAIL: $3 = %0d (expected 7)", dut.dp.regfile_inst.regs[3]);
                $finish;
            end
        end

        $display("\n❌ FAIL: Simulation timed out without encountering HALT.");
        $finish;
    end
endmodule

multi/mini_test.vcd
$date
	Tue Jun 03 16:03:32 2025
$end
$version
	Icarus Verilog
$end
$timescale
	1ps
$end
$scope module testbench $end
$var reg 1 ! clk $end
$var reg 1 " reset $end
$scope module dut $end
$var wire 1 ! clk $end
$var wire 1 " reset $end
$var wire 1 # Zero $end
$var wire 1 $ RegWrite $end
$var wire 1 % RegDst $end
$var wire 1 & PCWriteCond $end
$var wire 1 ' PCWrite $end
$var wire 2 ( PCSource [1:0] $end
$var wire 32 ) PC [31:0] $end
$var wire 1 * MemtoReg $end
$var wire 1 + MemWrite $end
$var wire 1 , MemRead $end
$var wire 32 - MemDataOut [31:0] $end
$var wire 32 . MemDataIn [31:0] $end
$var wire 1 / IorD $end
$var wire 32 0 Instr [31:0] $end
$var wire 1 1 IRWrite $end
$var wire 32 2 IR [31:0] $end
$var wire 2 3 ALUSrcB [1:0] $end
$var wire 1 4 ALUSrcA $end
$var wire 3 5 ALUControl [2:0] $end
$var wire 32 6 ALUAddr [31:0] $end
$scope module ctrl_unit $end
$var wire 1 ! clk $end
$var wire 1 " reset $end
$var wire 1 # Zero $end
$var wire 32 7 IR [31:0] $end
$var parameter 4 8 BRANCH $end
$var parameter 4 9 DECODE $end
$var parameter 4 : FETCH $end
$var parameter 4 ; I_EXEC $end
$var parameter 4 < I_WRITE $end
$var parameter 4 = JUMP $end
$var parameter 4 > MEM_ACCESS $end
$var parameter 4 ? R_EXEC $end
$var parameter 4 @ R_WRITE $end
$var reg 3 A ALUControl [2:0] $end
$var reg 1 4 ALUSrcA $end
$var reg 2 B ALUSrcB [1:0] $end
$var reg 1 1 IRWrite $end
$var reg 1 / IorD $end
$var reg 1 , MemRead $end
$var reg 1 + MemWrite $end
$var reg 1 * MemtoReg $end
$var reg 2 C PCSource [1:0] $end
$var reg 1 ' PCWrite $end
$var reg 1 & PCWriteCond $end
$var reg 1 % RegDst $end
$var reg 1 $ RegWrite $end
$var reg 4 D next_state [3:0] $end
$var reg 4 E state [3:0] $end
$upscope $end
$scope module data_memory $end
$var wire 1 + MemWrite $end
$var wire 1 ! clk $end
$var wire 32 F read_data [31:0] $end
$var wire 32 G write_data [31:0] $end
$var wire 32 H address [31:0] $end
$upscope $end
$scope module dp $end
$var wire 3 I ALUControl [2:0] $end
$var wire 1 4 ALUSrcA $end
$var wire 2 J ALUSrcB [1:0] $end
$var wire 1 1 IRWrite $end
$var wire 32 K IR_out [31:0] $end
$var wire 1 / IorD $end
$var wire 32 L MemDataIn [31:0] $end
$var wire 32 M MemDataOut [31:0] $end
$var wire 1 , MemRead $end
$var wire 1 N MemReadOut $end
$var wire 1 + MemWrite $end
$var wire 1 O MemWriteOut $end
$var wire 1 * MemtoReg $end
$var wire 32 P PC [31:0] $end
$var wire 2 Q PCSource [1:0] $end
$var wire 1 ' PCWrite $end
$var wire 1 & PCWriteCond $end
$var wire 1 % RegDst $end
$var wire 1 $ RegWrite $end
$var wire 1 # Zero $end
$var wire 1 ! clk $end
$var wire 1 " reset $end
$var wire 32 R rd2 [31:0] $end
$var wire 32 S rd1 [31:0] $end
$var wire 5 T WriteReg [4:0] $end
$var wire 32 U WriteData [31:0] $end
$var wire 32 V SignImm [31:0] $end
$var wire 32 W Instr [31:0] $end
$var wire 1 X ALU_zero $end
$var wire 32 Y ALU_src_A [31:0] $end
$var wire 32 Z ALU_result [31:0] $end
$var wire 32 [ ALUAddr [31:0] $end
$var reg 32 \ ALUOut [31:0] $end
$var reg 32 ] ALU_src_B [31:0] $end
$var reg 32 ^ A_reg [31:0] $end
$var reg 32 _ B_reg [31:0] $end
$var reg 32 ` IR [31:0] $end
$var reg 32 a MDR [31:0] $end
$var reg 32 b PC_reg [31:0] $end
$scope module alu_inst $end
$var wire 32 c A [31:0] $end
$var wire 3 d ALUControl [2:0] $end
$var wire 32 e B [31:0] $end
$var wire 1 X Zero $end
$var reg 32 f Result [31:0] $end
$upscope $end
$scope module regfile_inst $end
$var wire 1 $ RegWrite $end
$var wire 1 ! clk $end
$var wire 5 g ra1 [4:0] $end
$var wire 5 h ra2 [4:0] $end
$var wire 32 i rd1 [31:0] $end
$var wire 32 j rd2 [31:0] $end
$var wire 5 k wa [4:0] $end
$var wire 32 l wd [31:0] $end
$var integer 32 m i [31:0] $end
$upscope $end
$upscope $end
$scope module instr_memory $end
$var wire 32 n address [31:0] $end
$var wire 32 o instr [31:0] $end
$upscope $end
$upscope $end
$upscope $end
$enddefinitions $end
$comment Show the parameter values. $end
$dumpall
b11 @
b10 ?
b101 >
b1000 =
b110 <
b100 ;
b0 :
b1 9
b111 8
$end
#0
$dumpvars
b100000000000010000000000000011 o
b0 n
b100000 m
bx l
bx k
bx j
bx i
bx h
bx g
b100 f
b100 e
b0 d
b0 c
b0 b
bx a
bx `
bx _
bx ^
b100 ]
bx \
b0 [
b100 Z
b0 Y
0X
b100000000000010000000000000011 W
bx V
bx U
bx T
bx S
bx R
b0 Q
b0 P
0O
1N
bx M
bx L
bx K
b1 J
b0 I
b0 H
bx G
bx F
b0 E
b1 D
b0 C
b1 B
b0 A
bx 7
b0 6
b0 5
04
b1 3
bx 2
11
b100000000000010000000000000011 0
0/
bx .
bx -
1,
0+
0*
b0 )
b0 (
1'
0&
0%
0$
0#
1"
0!
$end
#5000
b1 T
b1 k
b11 V
b0 S
b0 i
b0 g
b0 R
b0 j
b1 h
b1 D
b1 3
b1 B
b1 J
11
1N
1,
1'
b100 U
b100 l
b100000000000010000000000000011 2
b100000000000010000000000000011 7
b100000000000010000000000000011 K
b100000000000010000000000000011 `
b100 \
1!
#10000
0!
0"
#15000
b1100 ]
b1100 e
b10000 Z
b10000 f
b100 D
b11 3
b11 B
b11 J
01
0N
0,
0'
b100 6
b100 H
b100 [
b100 Y
b100 c
b100000000000100000000000000100 0
b100000000000100000000000000100 W
b100000000000100000000000000100 o
b1 E
b100 )
b100 P
b100 n
b100 b
b0 -
b0 G
b0 M
b0 _
b0 ^
1!
#20000
0!
#25000
b11 Z
b11 f
b0 Y
b0 c
b11 ]
b11 e
14
b110 D
b10 3
b10 B
b10 J
b10000 U
b10000 l
b100 E
b10000 \
1!
#30000
0!
#35000
b100 Z
b100 f
b0 ]
b0 e
b100 Y
b100 c
1$
b0 D
b0 3
b0 B
b0 J
04
b11 U
b11 l
b110 E
b11 \
1!
#40000
0!
#45000
b1000 Z
b1000 f
b100 ]
b100 e
b1 D
1'
b1 3
b1 B
b1 J
11
1N
1,
0$
b100 U
b100 l
b0 E
b11 R
b11 j
b100 \
1!
#50000
0!
#55000
b11000 Z
b11000 f
b10 T
b10 k
b1000 6
b1000 H
b1000 [
b1000 Y
b1000 c
b1000100001100000100000 0
b1000100001100000100000 W
b1000100001100000100000 o
b1000 U
b1000 l
b10000 ]
b10000 e
b100 V
b0 R
b0 j
b10 h
b100 D
b11 3
b11 B
b11 J
01
0N
0,
0'
b1 E
b1000 )
b1000 P
b1000 n
b1000 b
b1000 \
b11 -
b11 G
b11 M
b11 _
b100000000000100000000000000100 2
b100000000000100000000000000100 7
b100000000000100000000000000100 K
b100000000000100000000000000100 `
1!
#60000
0!
#65000
b100 Z
b100 f
b0 Y
b0 c
b100 ]
b100 e
14
b110 D
b10 3
b10 B
b10 J
b11000 U
b11000 l
b100 E
b0 -
b0 G
b0 M
b0 _
b11000 \
1!
#70000
0!
#75000
b1000 Z
b1000 f
b0 ]
b0 e
b1000 Y
b1000 c
1$
b0 D
b0 3
b0 B
b0 J
04
b100 U
b100 l
b110 E
b100 \
1!
#80000
0!
#85000
b1100 Z
b1100 f
b100 ]
b100 e
b1 D
1'
b1 3
b1 B
b1 J
11
1N
1,
0$
b1000 U
b1000 l
b0 E
b100 R
b100 j
b1000 \
1!
#90000
0!
#95000
b110000010001100 Z
b110000010001100 f
b1100 6
b1100 H
b1100 [
b1100 Y
b1100 c
bx 0
bx W
bx o
b1100 U
b1100 l
b110000010000000 ]
b110000010000000 e
b1100000100000 V
b11 S
b11 i
b1 g
b10 D
b11 3
b11 B
b11 J
01
0N
0,
0'
b1 E
b1100 )
b1100 P
b1100 n
b1100 b
b1100 \
b100 -
b100 G
b100 M
b100 _
b1000100001100000100000 2
b1000100001100000100000 7
b1000100001100000100000 K
b1000100001100000100000 `
1!
#100000
0!
#105000
b111 Z
b111 f
b11 Y
b11 c
b100 ]
b100 e
14
b11 D
b0 3
b0 B
b0 J
b110000010001100 U
b110000010001100 l
b10 E
b11 ^
b110000010001100 \
1!
#110000
0!
#115000
b10000 Z
b10000 f
b11 T
b11 k
b1100 Y
b1100 c
1%
1$
b0 D
04
b111 U
b111 l
b11 E
b111 \
1!
#120000
0!
#125000
b10 T
b10 k
b1 D
1'
b1 3
b1 B
b1 J
11
1N
1,
0$
0%
b10000 U
b10000 l
b0 E
b10000 \
1!
#130000
0!
#135000
x#
xX
bx Z
bx f
bx T
bx k
bx00 ]
bx00 e
b10000 6
b10000 H
b10000 [
b10000 Y
b10000 c
bx V
bx S
bx i
bx g
bx R
bx j
bx h
b0 D
b11 3
b11 B
b11 J
01
0N
0,
0'
b1 E
b10000 )
b10000 P
b10000 n
b10000 b
bx 2
bx 7
bx K
bx `
1!
#140000
0!
#145000
0#
0X
b10100 Z
b10100 f
b100 ]
b100 e
b1 D
1'
11
1N
1,
b1 3
b1 B
b1 J
bx U
bx l
b0 E
bx -
bx G
bx M
bx _
bx ^
bx \
1!
#150000
0!
#155000
x#
xX
bx00 ]
bx00 e
bx Z
bx f
b0 D
b11 3
b11 B
b11 J
01
0N
0,
0'
b10100 6
b10100 H
b10100 [
b10100 Y
b10100 c
b10100 U
b10100 l
b1 E
b10100 )
b10100 P
b10100 n
b10100 b
b10100 \
1!
#160000
0!
#165000
0#
0X
b11000 Z
b11000 f
b100 ]
b100 e
b1 D
1'
11
1N
1,
b1 3
b1 B
b1 J
bx U
bx l
b0 E
bx \
1!
#170000
0!
#175000
x#
xX
bx00 ]
bx00 e
bx Z
bx f
b0 D
b11 3
b11 B
b11 J
01
0N
0,
0'
b11000 6
b11000 H
b11000 [
b11000 Y
b11000 c
b11000 U
b11000 l
b1 E
b11000 )
b11000 P
b11000 n
b11000 b
b11000 \
1!
#180000
0!
#185000
0#
0X
b11100 Z
b11100 f
b100 ]
b100 e
b1 D
1'
11
1N
1,
b1 3
b1 B
b1 J
bx U
bx l
b0 E
bx \
1!
#190000
0!
#195000
x#
xX
bx00 ]
bx00 e
bx Z
bx f
b0 D
b11 3
b11 B
b11 J
01
0N
0,
0'
b11100 6
b11100 H
b11100 [
b11100 Y
b11100 c
b11100 U
b11100 l
b1 E
b11100 )
b11100 P
b11100 n
b11100 b
b11100 \
1!
#200000
0!
#205000
0#
0X
b100000 Z
b100000 f
b100 ]
b100 e
b1 D
1'
11
1N
1,
b1 3
b1 B
b1 J
bx U
bx l
b0 E
bx \
1!
#210000
0!
#215000
x#
xX
bx00 ]
bx00 e
bx Z
bx f
b0 D
b11 3
b11 B
b11 J
01
0N
0,
0'
b100000 6
b100000 H
b100000 [
b100000 Y
b100000 c
b100000 U
b100000 l
b1 E
b100000 )
b100000 P
b100000 n
b100000 b
b100000 \
1!
#220000
0!
#225000
0#
0X
b100100 Z
b100100 f
b100 ]
b100 e
b1 D
1'
11
1N
1,
b1 3
b1 B
b1 J
bx U
bx l
b0 E
bx \
1!
#230000
0!
#235000
x#
xX
bx00 ]
bx00 e
bx Z
bx f
b0 D
b11 3
b11 B
b11 J
01
0N
0,
0'
b100100 6
b100100 H
b100100 [
b100100 Y
b100100 c
b100100 U
b100100 l
b1 E
b100100 )
b100100 P
b100100 n
b100100 b
b100100 \
1!
#240000
0!
#245000
0#
0X
b101000 Z
b101000 f
b100 ]
b100 e
b1 D
1'
11
1N
1,
b1 3
b1 B
b1 J
bx U
bx l
b0 E
bx \
1!
#250000
0!
#255000
x#
xX
bx00 ]
bx00 e
bx Z
bx f
b0 D
b11 3
b11 B
b11 J
01
0N
0,
0'
b101000 6
b101000 H
b101000 [
b101000 Y
b101000 c
b101000 U
b101000 l
b1 E
b101000 )
b101000 P
b101000 n
b101000 b
b101000 \
1!
#260000
0!
#265000
0#
0X
b101100 Z
b101100 f
b100 ]
b100 e
b1 D
1'
11
1N
1,
b1 3
b1 B
b1 J
bx U
bx l
b0 E
bx \
1!
#270000
0!
#275000
x#
xX
bx00 ]
bx00 e
bx Z
bx f
b0 D
b11 3
b11 B
b11 J
01
0N
0,
0'
b101100 6
b101100 H
b101100 [
b101100 Y
b101100 c
b101100 U
b101100 l
b1 E
b101100 )
b101100 P
b101100 n
b101100 b
b101100 \
1!
#280000
0!
#285000
0#
0X
b110000 Z
b110000 f
b100 ]
b100 e
b1 D
1'
11
1N
1,
b1 3
b1 B
b1 J
bx U
bx l
b0 E
bx \
1!
#290000
0!
#295000
x#
xX
bx00 ]
bx00 e
bx Z
bx f
b0 D
b11 3
b11 B
b11 J
01
0N
0,
0'
b110000 6
b110000 H
b110000 [
b110000 Y
b110000 c
b110000 U
b110000 l
b1 E
b110000 )
b110000 P
b110000 n
b110000 b
b110000 \
1!
#300000
0!
#305000
0#
0X
b110100 Z
b110100 f
b100 ]
b100 e
b1 D
1'
11
1N
1,
b1 3
b1 B
b1 J
bx U
bx l
b0 E
bx \
1!
#310000
0!
#315000
x#
xX
bx00 ]
bx00 e
bx Z
bx f
b0 D
b11 3
b11 B
b11 J
01
0N
0,
0'
b110100 6
b110100 H
b110100 [
b110100 Y
b110100 c
b110100 U
b110100 l
b1 E
b110100 )
b110100 P
b110100 n
b110100 b
b110100 \
1!
#320000
0!
#325000
0#
0X
b111000 Z
b111000 f
b100 ]
b100 e
b1 D
1'
11
1N
1,
b1 3
b1 B
b1 J
bx U
bx l
b0 E
bx \
1!
#330000
0!
#335000
x#
xX
bx00 ]
bx00 e
bx Z
bx f
b0 D
b11 3
b11 B
b11 J
01
0N
0,
0'
b111000 6
b111000 H
b111000 [
b111000 Y
b111000 c
b111000 U
b111000 l
b1 E
b111000 )
b111000 P
b111000 n
b111000 b
b111000 \
1!
#340000
0!
#345000
0#
0X
b111100 Z
b111100 f
b100 ]
b100 e
b1 D
1'
11
1N
1,
b1 3
b1 B
b1 J
bx U
bx l
b0 E
bx \
1!
#350000
0!
#355000
x#
xX
bx00 ]
bx00 e
bx Z
bx f
b0 D
b11 3
b11 B
b11 J
01
0N
0,
0'
b111100 6
b111100 H
b111100 [
b111100 Y
b111100 c
b111100 U
b111100 l
b1 E
b111100 )
b111100 P
b111100 n
b111100 b
b111100 \
1!
#360000
0!
